{
    "iteration": "January 2022",
    "submission-deadline": "2022-01-15",
    "review-deadline": "2022-02-15",
    "meta-deadline": "2022-02-20",
    "notification": "2022-02-21",
    "submissions": 1897,
    "active-submissions": 1774,
    "withdrawn": 11,
    "desk-rejects": 112,
    "ae-pool": 354,
    "rev-pool": 3715,
    "preprint": 669,
    "existing-preprint": 314,
    "resubmissions": 593,
    "reassignments": 158,
    "ae-assigned-reviewed": 17,
    "ae-assigned": 297,
    "rev-assigned-reviewed": 2064,
    "rev-assigned": 2538,
    "requested-revs": 6485,
    "returned-revs": 5086,
    "requested-mrevs": 1777,
    "returned-mrevs": 39,
    "meta-progress": 2.2,
    "rev-progress": 68.55,
    "ethical-concerns": 251
}