{
    "iteration": "December 2022",
    "submission-deadline": "2022-12-15",
    "review-deadline": "2023-01-23",
    "meta-deadline": "2023-02-08",
    "notification": "2023-02-15",
    "submissions": 502,
    "active-submissions": 407,
    "withdrawn": 83,
    "desk-rejects": 12,
    "ae-pool": 330,
    "rev-pool": 4945,
    "update-date": "2023-07-06",
    "preprint": 174,
    "existing-preprint": 98,
    "resubmissions": 138,
    "reassignments": 0,
    "ae-assigned-reviewed": 179,
    "ae-assigned": 181,
    "rev-assigned-reviewed": 916,
    "rev-assigned": 985,
    "requested-revs": 1698,
    "returned-revs": 1522,
    "requested-mrevs": 541,
    "returned-mrevs": 442,
    "meta-progress": 108.6,
    "rev-progress": 114.5,
    "ethical-concerns": 85
}