{
    "iteration": "September 2021",
    "submission-deadline": "2021-09-15",
    "review-deadline": "2021-10-15",
    "meta-deadline": "2021-10-20",
    "submissions": 312,
    "active-submissions": 278,
    "withdrawn": 29,
    "desk-rejects": 5,
    "ae-pool": 204,
    "rev-pool": 1537,
    "preprint": 85,
    "existing-preprint": 49,
    "resubmissions": 6,
    "reassignments": 0,
    "ae-assigned-reviewed": 111,
    "ae-assigned": 103,
    "rev-assigned-reviewed": 563,
    "rev-assigned": 557,
    "requested-revs": 893,
    "returned-revs": 843,
    "requested-mrevs": 304,
    "returned-mrevs": 247,
    "meta-progress": 88.85,
    "rev-progress": 92.09,
    "ethical-concerns": 63
}