{
    "iteration": "December 2024",
    "update-date": "2025-04-14",
    "submission-deadline": "2024-12-15",
    "review-deadline": "2025-01-21",
    "meta-deadline": "2025-02-04",
    "notification": "2025-02-15",
    "submissions": 2383,
    "withdrawn": 255,
    "desk-rejects": 144,
    "active-submissions": 1984,
    "ae-pool": 1669,
    "rev-pool": 11166,
    "preprint": 666,
    "existing-preprint": 538,
    "resubmissions": 569,
    "reassignments": 283,
    "rev-assigned": 2330,
    "ae-assigned": 446,
    "ae-assigned-reviewed": 1987,
    "rev-assigned-reviewed": 6249,
    "requested-revs": 7579,
    "returned-revs": 6249,
    "requested-mrevs": 2042,
    "returned-mrevs": 1987,
    "meta-progress": 100.0,
    "rev-progress": 99.8,
    "ethical-concerns": 46
}